{
  "_class": "group",
  "booleanOperation": -1,
  "clippingMaskMode": 0,
  "do_objectID": "00A36F25-7466-400C-AF26-CD269B13F83B",
  "exportOptions": {
    "_class": "exportOptions",
    "exportFormats": [
    ],
    "includedLayerIds": [
    ],
    "layerOptions": 0,
    "shouldTrim": false
  },
  "frame": {
    "_class": "rect",
    "constrainProportions": false,
    "height": 114,
    "width": 926,
    "x": 0,
    "y": 3727.5
  },
  "groupLayout": {
    "_class": "MSImmutableFreeformGroupLayout"
  },
  "hasClickThrough": false,
  "hasClippingMask": false,
  "isFixedToViewport": false,
  "isFlippedHorizontal": false,
  "isFlippedVertical": false,
  "isLocked": false,
  "isVisible": true,
  "layerListExpandedType": 0,
  "layers": [
    {
      "class": "rectangle",
      "id": "AE573B0B-A11B-4949-86A2-98B14431788A"
    },
    {
      "class": "shapePath",
      "id": "00BA18E5-7E90-458E-923A-049720834E97"
    },
    {
      "class": "text",
      "id": "C8FD1EDD-514E-432B-A390-38D573E4FF5D"
    },
    {
      "class": "symbolInstance",
      "id": "526B58F4-E028-4427-B3C2-4CB9687F50F2"
    }
  ],
  "name": "language accordion",
  "nameIsFixed": true,
  "resizingConstraint": 63,
  "resizingType": 0,
  "rotation": 0,
  "shouldBreakMaskChain": false,
  "style": {
    "_class": "style",
    "endMarkerType": 0,
    "miterLimit": 10,
    "startMarkerType": 0,
    "windingRule": 1
  }
}