{
  "_class": "artboard",
  "backgroundColor": {
    "_class": "color",
    "alpha": 1,
    "blue": 1,
    "green": 1,
    "red": 1
  },
  "booleanOperation": -1,
  "clippingMaskMode": 0,
  "do_objectID": "CA28DFE7-AB3D-4A24-9230-B8463D15AFA5",
  "exportOptions": {
    "_class": "exportOptions",
    "exportFormats": [
    ],
    "includedLayerIds": [
    ],
    "layerOptions": 0,
    "shouldTrim": false
  },
  "frame": {
    "_class": "rect",
    "constrainProportions": false,
    "height": 3840,
    "width": 925,
    "x": 2164,
    "y": 2909
  },
  "groupLayout": {
    "_class": "MSImmutableFreeformGroupLayout"
  },
  "hasBackgroundColor": false,
  "hasClickThrough": true,
  "hasClippingMask": false,
  "horizontalRulerData": {
    "_class": "rulerData",
    "base": 0,
    "guides": [
    ]
  },
  "includeBackgroundColorInExport": true,
  "includeInCloudUpload": true,
  "isFixedToViewport": false,
  "isFlippedHorizontal": false,
  "isFlippedVertical": false,
  "isFlowHome": false,
  "isLocked": false,
  "isVisible": true,
  "layerListExpandedType": 0,
  "layers": [
    {
      "class": "rectangle",
      "id": "57F0D380-DC89-4AD9-8FC4-FEA82C1FD4FF"
    },
    {
      "class": "group",
      "id": "4DC8B0F1-B539-42E4-87BC-EB1D7499678E"
    },
    {
      "class": "text",
      "id": "4A9CFEC9-51C8-4227-864D-10586C3CC562"
    },
    {
      "class": "group",
      "id": "DEBB3E8F-C062-479F-88F7-9B3EEA164729"
    },
    {
      "class": "rectangle",
      "id": "54002E86-E47B-4808-B447-4EC1D17C49C3"
    },
    {
      "class": "rectangle",
      "id": "FE80F5BC-D87F-435C-9039-A291AAC33846"
    },
    {
      "class": "rectangle",
      "id": "1609C5FF-8BFE-4F51-B274-5EB784FA9F4B"
    },
    {
      "class": "rectangle",
      "id": "1FCCF14B-7BD0-4D8A-A235-865DF8E55040"
    },
    {
      "class": "bitmap",
      "id": "934B7D5C-1A3A-47C0-BC3A-013409136F0B"
    },
    {
      "class": "text",
      "id": "3FBBED9A-D76D-4889-8AE4-6F28BAC9EF69"
    },
    {
      "class": "text",
      "id": "81B72F60-C4AA-4B48-908F-5BABDB497087"
    },
    {
      "class": "text",
      "id": "01B7248E-52F4-475E-A3CB-B5532FA480E6"
    }
  ],
  "name": "digital label",
  "nameIsFixed": false,
  "presetDictionary": {
    "allowResizedMatching": 0,
    "height": 3840,
    "name": "digital label",
    "offersLandscapeVariant": 0,
    "width": 925
  },
  "resizesContent": false,
  "resizingConstraint": 63,
  "resizingType": 0,
  "rotation": 0,
  "shouldBreakMaskChain": true,
  "style": {
    "_class": "style",
    "endMarkerType": 0,
    "miterLimit": 10,
    "startMarkerType": 0,
    "windingRule": 1
  },
  "verticalRulerData": {
    "_class": "rulerData",
    "base": 0,
    "guides": [
    ]
  }
}