{
  "_class": "text",
  "attributedString": {
    "_class": "attributedString",
    "attributes": [
      {
        "_class": "stringAttribute",
        "attributes": {
          "MSAttributedStringColorAttribute": {
            "_class": "color",
            "alpha": 1,
            "blue": 0,
            "green": 0,
            "red": 0
          },
          "MSAttributedStringFontAttribute": {
            "_class": "fontDescriptor",
            "attributes": {
              "name": "AvenirLTPro-Roman",
              "size": 30
            }
          },
          "paragraphStyle": {
            "_class": "paragraphStyle",
            "alignment": 0,
            "allowsDefaultTighteningForTruncation": 0,
            "baseWritingDirection": 0,
            "maximumLineHeight": 40,
            "minimumLineHeight": 40,
            "tighteningFactorForTruncation": 0.05
          },
          "textStyleVerticalAlignmentKey": 0
        },
        "length": 5,
        "location": 0
      }
    ],
    "string": "GL208"
  },
  "automaticallyDrawOnUnderlyingPath": false,
  "booleanOperation": -1,
  "clippingMaskMode": 0,
  "do_objectID": "07F922DE-68C9-46D1-85B7-1857CFE88BE5",
  "dontSynchroniseWithSymbol": false,
  "exportOptions": {
    "_class": "exportOptions",
    "do_objectID": "35810FCB-8483-4C21-8323-5A9EFC2DB60E",
    "exportFormats": [
    ],
    "includedLayerIds": [
    ],
    "layerOptions": 0,
    "shouldTrim": false
  },
  "frame": {
    "_class": "rect",
    "constrainProportions": false,
    "do_objectID": "7B37FB2B-0862-423C-9559-13894E1950DE",
    "height": 160,
    "width": 851,
    "x": 30,
    "y": 2096
  },
  "glyphBounds": "{{1, 12}, {86, 23}}",
  "hasClippingMask": false,
  "isFixedToViewport": false,
  "isFlippedHorizontal": false,
  "isFlippedVertical": false,
  "isLocked": false,
  "isVisible": true,
  "layerListExpandedType": 0,
  "lineSpacingBehaviour": 2,
  "name": "GL208",
  "nameIsFixed": false,
  "resizingConstraint": 63,
  "resizingType": 0,
  "rotation": 0,
  "sharedStyleID": "E41D9FCD-314B-4D2C-B387-1853F4FCC46F",
  "shouldBreakMaskChain": false,
  "style": {
    "_class": "style",
    "do_objectID": "C9106AC0-DA18-4994-A44F-B0545CE6EB72",
    "endMarkerType": 0,
    "miterLimit": 10,
    "startMarkerType": 0,
    "textStyle": {
      "_class": "textStyle",
      "do_objectID": "AA412630-6515-4C13-B991-CE43C8691A4A",
      "encodedAttributes": {
        "MSAttributedStringColorAttribute": {
          "_class": "color",
          "alpha": 1,
          "blue": 0,
          "green": 0,
          "red": 0
        },
        "MSAttributedStringFontAttribute": {
          "_class": "fontDescriptor",
          "attributes": {
            "name": "AvenirLTPro-Roman",
            "size": 30
          }
        },
        "paragraphStyle": {
          "_class": "paragraphStyle",
          "alignment": 0,
          "allowsDefaultTighteningForTruncation": 0,
          "baseWritingDirection": 0,
          "maximumLineHeight": 40,
          "minimumLineHeight": 40,
          "tighteningFactorForTruncation": 0.05
        },
        "textStyleVerticalAlignmentKey": 0
      },
      "verticalAlignment": 0
    },
    "windingRule": 1
  },
  "textBehaviour": 2,
  "userInfo": {
    "com.animaapp.stc-sketch-plugin": {
      "kModelPropertiesKey": {
        "isAutoWidth": 0
      }
    }
  }
}