{
  "_class": "group",
  "booleanOperation": -1,
  "clippingMaskMode": 0,
  "do_objectID": "A12A9F22-5CB6-4CC7-90E1-D2DE7171BCB9",
  "exportOptions": {
    "_class": "exportOptions",
    "exportFormats": [
    ],
    "includedLayerIds": [
    ],
    "layerOptions": 0,
    "shouldTrim": false
  },
  "frame": {
    "_class": "rect",
    "constrainProportions": false,
    "height": 250,
    "width": 992,
    "x": -51,
    "y": 1333
  },
  "groupLayout": {
    "_class": "MSImmutableFreeformGroupLayout"
  },
  "hasClickThrough": false,
  "hasClippingMask": false,
  "isFixedToViewport": false,
  "isFlippedHorizontal": false,
  "isFlippedVertical": false,
  "isLocked": false,
  "isVisible": true,
  "layerListExpandedType": 0,
  "layers": [
    {
      "class": "group",
      "id": "51BCB10C-B67D-4103-ABC1-7A2459950EC2"
    },
    {
      "class": "rectangle",
      "id": "116D98B7-5CA2-40FA-B91F-860F68631085"
    },
    {
      "class": "symbolInstance",
      "id": "EDA4886D-0C4F-4E1F-A2D9-84822C698A3A"
    }
  ],
  "name": "accordion 4",
  "nameIsFixed": true,
  "resizingConstraint": 63,
  "resizingType": 0,
  "rotation": 0,
  "shouldBreakMaskChain": false,
  "style": {
    "_class": "style",
    "endMarkerType": 0,
    "miterLimit": 10,
    "startMarkerType": 0,
    "windingRule": 1
  }
}