{
  "_class": "group",
  "booleanOperation": -1,
  "clippingMaskMode": 0,
  "do_objectID": "197E894A-4AEA-4D55-807C-6622A37A9E61",
  "exportOptions": {
    "_class": "exportOptions",
    "exportFormats": [
    ],
    "includedLayerIds": [
    ],
    "layerOptions": 0,
    "shouldTrim": false
  },
  "frame": {
    "_class": "rect",
    "constrainProportions": false,
    "height": 250,
    "width": 992,
    "x": -25,
    "y": 604
  },
  "groupLayout": {
    "_class": "MSImmutableFreeformGroupLayout"
  },
  "hasClickThrough": false,
  "hasClippingMask": false,
  "isFixedToViewport": false,
  "isFlippedHorizontal": false,
  "isFlippedVertical": false,
  "isLocked": false,
  "isVisible": true,
  "layerListExpandedType": 2,
  "layers": [
    {
      "class": "group",
      "id": "8B4B9DA7-C87C-4DF0-BEF8-F11142FFDBD6"
    },
    {
      "class": "rectangle",
      "id": "D1544618-2BFC-46B7-A273-71E5B09D7E7C"
    },
    {
      "class": "symbolInstance",
      "id": "474F55EB-CC7D-4D94-84B9-A5C2C89FD638"
    }
  ],
  "name": "accordion 1",
  "nameIsFixed": true,
  "resizingConstraint": 63,
  "resizingType": 0,
  "rotation": 0,
  "shouldBreakMaskChain": false,
  "style": {
    "_class": "style",
    "endMarkerType": 0,
    "miterLimit": 10,
    "startMarkerType": 0,
    "windingRule": 1
  }
}